{"userProfileId": 124379277, "totalKilocalories": 3708.0, "activeKilocalories": 1583.0, "bmrKilocalories": 2125.0, "wellnessKilocalories": 3708.0, "burnedKilocalories": null, "consumedKilocalories": null, "remainingKilocalories": null, "totalSteps": 26460, "netCalorieGoal": null, "totalDistanceMeters": 24798, "wellnessDistanceMeters": 24798, "wellnessActiveKilocalories": 1583.0, "netRemainingKilocalories": 1583.0, "userDailySummaryId": 124379277, "calendarDate": "2025-02-01", "rule": {"typeId": 2, "typeKey": "private"}, "uuid": "8416de964f6d46cc8cd2a60385644514", "dailyStepGoal": 16580, "wellnessStartTimeGmt": "2025-02-01T06:00:00.0", "wellnessStartTimeLocal": "2025-02-01T00:00:00.0", "wellnessEndTimeGmt": "2025-02-02T06:00:00.0", "wellnessEndTimeLocal": "2025-02-02T00:00:00.0", "durationInMilliseconds": 86400000, "wellnessDescription": null, "highlyActiveSeconds": 7021, "activeSeconds": 7794, "sedentarySeconds": 46025, "sleepingSeconds": 25560, "includesWellnessData": true, "includesActivityData": true, "includesCalorieConsumedData": false, "privacyProtected": false, "moderateIntensityMinutes": 3, "vigorousIntensityMinutes": 93, "floorsAscendedInMeters": 79.656, "floorsDescendedInMeters": 58.719, "floorsAscended": 26.13386, "floorsDescended": 19.26476, "intensityMinutesGoal": 150, "userFloorsAscendedGoal": 10, "minHeartRate": 49, "maxHeartRate": 185, "restingHeartRate": 52, "lastSevenDaysAvgRestingHeartRate": 51, "source": "GARMIN", "averageStressLevel": 24, "maxStressLevel": 96, "stressDuration": 8580, "restStressDuration": 36720, "activityStressDuration": 13260, "uncategorizedStressDuration": 25860, "totalStressDuration": 84420, "lowStressDuration": 5100, "mediumStressDuration": 2280, "highStressDuration": 1200, "stressPercentage": 10.16, "restStressPercentage": 43.5, "activityStressPercentage": 15.71, "uncategorizedStressPercentage": 30.63, "lowStressPercentage": 6.04, "mediumStressPercentage": 2.7, "highStressPercentage": 1.42, "stressQualifier": "CALM", "measurableAwakeDuration": 33000, "measurableAsleepDuration": 25560, "lastSyncTimestampGMT": null, "minAvgHeartRate": 50, "maxAvgHeartRate": 184, "bodyBatteryChargedValue": 60, "bodyBatteryDrainedValue": 45, "bodyBatteryHighestValue": 76, "bodyBatteryLowestValue": 16, "bodyBatteryMostRecentValue": 20, "bodyBatteryDuringSleep": 59, "bodyBatteryAtWakeTime": 75, "bodyBatteryVersion": 3.0, "abnormalHeartRateAlertsCount": null, "averageSpo2": null, "lowestSpo2": null, "latestSpo2": null, "latestSpo2ReadingTimeGmt": null, "latestSpo2ReadingTimeLocal": null, "averageMonitoringEnvironmentAltitude": 295.0, "restingCaloriesFromActivity": 124.0, "bodyBatteryDynamicFeedbackEvent": {"eventTimestampGmt": "2025-02-02T03:56:52", "bodyBatteryLevel": "MODERATE", "feedbackShortType": "SLEEP_PREPARATION_NOT_STRESS_DATA_AND_INTENSIVE_EXERCISE", "feedbackLongType": "SLEEP_PREPARATION_NOT_STRESS_DATA_AND_INTENSIVE_EXERCISE"}, "endOfDayBodyBatteryDynamicFeedbackEvent": {"eventTimestampGmt": "2025-02-01T08:36:44", "bodyBatteryLevel": "HIGH", "feedbackShortType": "SLEEP_TIME_PASSED_BALANCED_AND_INACTIVE", "feedbackLongType": "SLEEP_TIME_PASSED_BALANCED_AND_INACTIVE"}, "bodyBatteryActivityEventList": [{"eventType": "SLEEP", "eventStartTimeGmt": "2025-02-01T07:00:28", "timezoneOffset": -21600000, "durationInMilliseconds": 25560000, "bodyBatteryImpact": 59, "feedbackType": "NONE", "shortFeedback": "NONE", "deviceId": 3459366507, "activityName": null, "activityType": null, "activityId": null, "eventUpdateTimeGmt": "2025-02-01T14:16:13"}, {"eventType": "ACTIVITY", "eventStartTimeGmt": "2025-02-01T16:34:30", "timezoneOffset": -21600000, "durationInMilliseconds": 5040000, "bodyBatteryImpact": -18, "feedbackType": "EXERCISE_TRAINING_EFFECT_4_GOOD_TIMING", "shortFeedback": "HIGHLY_IMPROVING_TEMPO", "deviceId": 3459366507, "activityName": "Madison - Long Run", "activityType": "running", "activityId": 18161875914, "eventUpdateTimeGmt": "2025-02-01T17:59:29"}], "avgWakingRespirationValue": 13.0, "highestRespirationValue": 19.0, "lowestRespirationValue": 6.0, "latestRespirationValue": 13.0, "latestRespirationTimeGMT": "2025-02-02T06:00:00.0", "respirationAlgorithmVersion": 100}