{"activityId": 18777869423, "activityName": "Madison Running", "startTimeLocal": "2025-04-08 18:14:21", "startTimeGMT": "2025-04-08 23:14:21", "activityType": {"typeId": 1, "typeKey": "running", "parentTypeId": 17, "isHidden": false, "trimmable": true, "restricted": false}, "eventType": {"typeId": 9, "typeKey": "uncategorized", "sortOrder": 10}, "distance": 352.55999755859375, "duration": 92.97100067138672, "elapsedDuration": 92.97100067138672, "movingDuration": 92.0, "elevationGain": 3.75, "elevationLoss": 0.0, "averageSpeed": 3.7920000553131104, "maxSpeed": 4.375999927520752, "startLatitude": 43.069948023185134, "startLongitude": -89.40945225767791, "hasPolyline": true, "hasImages": false, "ownerId": 124379277, "ownerDisplayName": "5fddc451-c515-4112-b457-4b306d9f603d", "ownerFullName": "Vikranth Mandadi", "ownerProfileImageUrlSmall": "https://s3.amazonaws.com/garmin-connect-prod/profile_images/d97b2398-0e5d-4ff5-82f8-988261803023-prth.png", "ownerProfileImageUrlMedium": "https://s3.amazonaws.com/garmin-connect-prod/profile_images/d97b2398-0e5d-4ff5-82f8-988261803023-prfr.png", "ownerProfileImageUrlLarge": "https://s3.amazonaws.com/garmin-connect-prod/profile_images/d97b2398-0e5d-4ff5-82f8-988261803023-prof.png", "calories": 18.0, "bmrCalories": 2.0, "averageHR": 137.0, "maxHR": 164.0, "averageRunningCadenceInStepsPerMinute": 170.390625, "maxRunningCadenceInStepsPerMinute": 187.0, "steps": 270, "userRoles": ["SCOPE_GOLF_API_READ", "SCOPE_ATP_READ", "SCOPE_DIVE_API_WRITE", "SCOPE_COMMUNITY_COURSE_ADMIN_READ", "SCOPE_DIVE_API_READ", "SCOPE_DI_OAUTH_2_CLIENT_READ", "SCOPE_CONNECT_WRITE", "SCOPE_COMMUNITY_COURSE_WRITE", "SCOPE_MESSAGE_GENERATION_READ", "SCOPE_DI_OAUTH_2_CLIENT_REVOCATION_ADMIN", "SCOPE_CONNECT_WEB_TEMPLATE_RENDER", "SCOPE_OMT_SUBSCRIPTION_ADMIN_READ", "SCOPE_CONNECT_NON_SOCIAL_SHARED_READ", "SCOPE_CONNECT_READ", "SCOPE_DI_OAUTH_2_TOKEN_ADMIN", "ROLE_CONNECTUSER", "ROLE_FITNESS_USER", "ROLE_WELLNESS_USER", "ROLE_OUTDOOR_USER"], "privacy": {"typeId": 2, "typeKey": "private"}, "userPro": false, "hasVideo": false, "timeZoneId": 152, "beginTimestamp": 1744154061000, "sportTypeId": 1, "avgPower": 439.0, "maxPower": 513.0, "aerobicTrainingEffect": 0.30000001192092896, "anaerobicTrainingEffect": 0.0, "normPower": 473.0, "avgVerticalOscillation": 9.20999984741211, "avgGroundContactTime": 219.39999389648438, "avgStrideLength": 135.4800048828125, "avgVerticalRatio": 6.820000171661377, "deviceId": 3459366507, "minElevation": 264.6000061035156, "maxElevation": 268.6000061035156, "maxDoubleCadence": 187.0, "summarizedDiveInfo": {"summarizedDiveGases": []}, "maxVerticalSpeed": 0.20001220703125003, "manufacturer": "GARMIN", "locationName": "Madison", "lapCount": 1, "endLatitude": 43.07271916419268, "endLongitude": -89.40832153894007, "waterEstimated": 25.0, "trainingEffectLabel": "UNKNOWN", "activityTrainingLoad": 4.1153717041015625, "minActivityLapDuration": 92.97100067138672, "aerobicTrainingEffectMessage": "NO_AEROBIC_BENEFIT_18", "anaerobicTrainingEffectMessage": "NO_ANAEROBIC_BENEFIT_0", "splitSummaries": [{"noOfSplits": 1, "totalAscent": 3.189999997615814, "duration": 92.97100067138672, "splitType": "INTERVAL_ACTIVE", "numClimbSends": 0, "maxElevationGain": 3.189999997615814, "averageElevationGain": 1.25, "maxDistance": 352, "distance": 352.55999755859375, "averageSpeed": 3.7920000553131104, "maxSpeed": 4.375999927520752, "numFalls": 0, "elevationLoss": 0.0}, {"noOfSplits": 1, "totalAscent": 3.189999997615814, "duration": 92.76699829101562, "splitType": "RWD_RUN", "numClimbSends": 0, "maxElevationGain": 3.189999997615814, "averageElevationGain": 3.189999997615814, "maxDistance": 352, "distance": 352.55999755859375, "averageSpeed": 3.799999952316284, "maxSpeed": 4.375999927520752, "numFalls": 0, "elevationLoss": 0.0}], "hasSplits": true, "moderateIntensityMinutes": 0, "vigorousIntensityMinutes": 0, "avgGradeAdjustedSpeed": 4.203000068664551, "differenceBodyBattery": 0, "hasHeatMap": false, "hrTimeInZone_1": 25.996, "hrTimeInZone_2": 27.0, "hrTimeInZone_3": 30.812, "hrTimeInZone_4": 0.0, "hrTimeInZone_5": 0.0, "powerTimeInZone_1": 0.0, "powerTimeInZone_2": 0.0, "powerTimeInZone_3": 1.991, "powerTimeInZone_4": 27.804, "powerTimeInZone_5": 56.0, "manualActivity": false, "pr": false, "autoCalcCalories": false, "elevationCorrected": false, "atpActivity": false, "favorite": false, "decoDive": false, "parent": false, "purposeful": false}