{"activityId": 18496662803, "activityUUID": {"uuid": "66d78e4c-44be-473d-a51d-657611c5d936"}, "activityName": "Madison Running", "userProfileId": 124379277, "isMultiSportParent": false, "activityTypeDTO": {"typeId": 1, "typeKey": "running", "parentTypeId": 17, "isHidden": false, "restricted": false, "trimmable": true}, "eventTypeDTO": {"typeId": 9, "typeKey": "uncategorized", "sortOrder": 10}, "accessControlRuleDTO": {"typeId": 2, "typeKey": "private"}, "timeZoneUnitDTO": {"unitId": 152, "unitKey": "America/Chicago", "factor": 0.0, "timeZone": "America/Chicago"}, "metadataDTO": {"isOriginal": true, "deviceApplicationInstallationId": 991247, "agentApplicationInstallationId": null, "agentString": null, "fileFormat": {"formatId": 7, "formatKey": "fit"}, "associatedCourseId": null, "lastUpdateDate": "2025-03-10T20:49:54.0", "uploadedDate": "2025-03-10T20:49:54.0", "videoUrl": null, "hasPolyline": true, "hasChartData": true, "hasHrTimeInZones": true, "hasPowerTimeInZones": true, "userInfoDto": {"userProfilePk": 124379277, "displayname": "5fddc451-c515-4112-b457-4b306d9f603d", "fullname": "Vikranth Mandadi", "profileImageUrlLarge": "https://s3.amazonaws.com/garmin-connect-prod/profile_images/d97b2398-0e5d-4ff5-82f8-988261803023-prof.png", "profileImageUrlMedium": "https://s3.amazonaws.com/garmin-connect-prod/profile_images/d97b2398-0e5d-4ff5-82f8-988261803023-prfr.png", "profileImageUrlSmall": "https://s3.amazonaws.com/garmin-connect-prod/profile_images/d97b2398-0e5d-4ff5-82f8-988261803023-prth.png", "userPro": false}, "childIds": [], "childActivityTypes": [], "sensors": null, "activityImages": [], "manufacturer": "GARMIN", "diveNumber": null, "lapCount": 6, "associatedWorkoutId": null, "isAtpActivity": null, "deviceMetaDataDTO": {"deviceId": "3459366507", "deviceTypePk": 36889, "deviceVersionPk": 991247}, "hasIntensityIntervals": false, "hasSplits": true, "eBikeMaxAssistModes": null, "eBikeBatteryUsage": null, "eBikeBatteryRemaining": null, "eBikeAssistModeInfoDTOList": null, "hasRunPowerWindData": true, "calendarEventInfo": null, "groupRideUUID": null, "hasHeatMap": false, "personalRecord": false, "manualActivity": false, "runPowerWindDataEnabled": true, "trimmed": false, "gcj02": false, "autoCalcCalories": false, "favorite": false, "elevationCorrected": false}, "summaryDTO": {"startTimeLocal": "2025-03-10T14:58:56.0", "startTimeGMT": "2025-03-10T19:58:56.0", "startLatitude": 43.06987904012203, "startLongitude": -89.40931932069361, "distance": 9142.83, "duration": 2929.795, "movingDuration": 2920.775, "elapsedDuration": 3004.416, "elevationGain": 34.23, "elevationLoss": 34.5, "maxElevation": 266.6, "minElevation": 255.6, "averageSpeed": 3.121000051498413, "averageMovingSpeed": 3.1302753882893017, "maxSpeed": 3.86299991607666, "calories": 696.0, "bmrCalories": 72.0, "averageHR": 165.0, "maxHR": 184.0, "minHR": 89.0, "averageRunCadence": 173.625, "maxRunCadence": 186.0, "averagePower": 340.0, "maxPower": 465.0, "minPower": 0.0, "normalizedPower": 344.0, "totalWork": 238.1850205965604, "groundContactTime": 251.89999389648438, "strideLength": 107.45, "verticalOscillation": 8.730000305175782, "trainingEffect": 3.5, "anaerobicTrainingEffect": 0.0, "aerobicTrainingEffectMessage": "IMPACTING_TEMPO_22", "anaerobicTrainingEffectMessage": "NO_ANAEROBIC_BENEFIT_0", "verticalRatio": 8.130000114440918, "endLatitude": 43.07016469538212, "endLongitude": -89.40281555056572, "maxVerticalSpeed": 1.0, "waterEstimated": 813.0, "trainingEffectLabel": "TEMPO", "activityTrainingLoad": 119.44564819335938, "minActivityLapDuration": 369.551, "moderateIntensityMinutes": 0, "vigorousIntensityMinutes": 48, "steps": 8486, "beginPotentialStamina": 100.0, "endPotentialStamina": 76.0, "minAvailableStamina": 76.0, "avgGradeAdjustedSpeed": 3.1300001144409184, "differenceBodyBattery": -11}, "locationName": "Madison", "splitSummaries": [{"distance": 9142.83, "duration": 2929.795, "movingDuration": 2920.0, "elevationGain": 34.95, "elevationLoss": 34.22, "averageSpeed": 3.121000051498413, "averageMovingSpeed": 3.1311061911386986, "maxSpeed": 3.86299991607666, "calories": 696.0, "bmrCalories": 72.0, "averageHR": 165.0, "maxHR": 184.0, "averageRunCadence": 173.609375, "maxRunCadence": 186.0, "averagePower": 340.0, "maxPower": 465.0, "normalizedPower": 344.0, "groundContactTime": 251.89999389648438, "strideLength": 107.45, "verticalOscillation": 8.730000305175782, "verticalRatio": 8.130000114440918, "totalExerciseReps": 0, "avgVerticalSpeed": 0.0, "avgGradeAdjustedSpeed": 0.0, "splitType": "INTERVAL_ACTIVE", "noOfSplits": 1, "maxElevationGain": 34.95, "averageElevationGain": 11.17, "maxDistance": 9142, "maxDistanceWithPrecision": 9142.83}, {"distance": 0.0, "duration": 7.006, "movingDuration": 0.0, "elevationGain": 0.0, "elevationLoss": 0.0, "averageSpeed": 0.0, "maxSpeed": 0.0, "calories": 0.0, "bmrCalories": 0.0, "averageHR": 90.0, "maxHR": 91.0, "averageRunCadence": 23.84375, "maxRunCadence": 167.0, "averagePower": 0.0, "maxPower": 0.0, "strideLength": 0.0, "totalExerciseReps": 0, "avgVerticalSpeed": 0.0, "avgGradeAdjustedSpeed": 0.0, "splitType": "RWD_STAND", "noOfSplits": 1, "maxElevationGain": 0.0, "averageElevationGain": 0.0, "maxDistance": 0, "maxDistanceWithPrecision": 0.0}, {"distance": 9132.99, "duration": 2918.391, "movingDuration": 2916.0, "elevationGain": 34.95, "elevationLoss": 34.22, "averageSpeed": 3.1289999485015874, "averageMovingSpeed": 3.132034548681916, "maxSpeed": 3.86299991607666, "calories": 696.0, "bmrCalories": 72.0, "averageHR": 166.0, "maxHR": 184.0, "averageRunCadence": 174.125, "maxRunCadence": 186.0, "averagePower": 342.0, "maxPower": 465.0, "normalizedPower": 344.0, "groundContactTime": 251.89999389648438, "strideLength": 107.46999511718751, "verticalOscillation": 8.730000305175782, "verticalRatio": 8.130000114440918, "totalExerciseReps": 0, "avgVerticalSpeed": 0.0, "avgGradeAdjustedSpeed": 3.1389999389648438, "splitType": "RWD_RUN", "noOfSplits": 2, "maxElevationGain": 27.12, "averageElevationGain": 17.75, "maxDistance": 7992, "maxDistanceWithPrecision": 7992.76}, {"distance": 9.85, "duration": 4.173, "movingDuration": 2.0, "elevationGain": 0.0, "elevationLoss": 0.0, "averageSpeed": 2.359999895095825, "averageMovingSpeed": 4.925000190734863, "maxSpeed": 2.575000047683716, "calories": 0.0, "bmrCalories": 0.0, "averageHR": 135.0, "maxHR": 135.0, "averageRunCadence": 57.5, "maxRunCadence": 115.0, "averagePower": 66.0, "maxPower": 141.0, "normalizedPower": 116.0, "strideLength": 86.80000000000001, "verticalOscillation": 6.090000152587891, "verticalRatio": 7.039999961853027, "totalExerciseReps": 0, "avgVerticalSpeed": 0.0, "avgGradeAdjustedSpeed": 1.9769999980926514, "splitType": "RWD_WALK", "noOfSplits": 2, "maxElevationGain": 0.0, "averageElevationGain": 0.0, "maxDistance": 9, "maxDistanceWithPrecision": 9.85}]}