{"activityId": 18849659726, "activityName": "Madison Running", "startTimeLocal": "2025-04-16 17:55:06", "startTimeGMT": "2025-04-16 22:55:06", "activityType": {"typeId": 1, "typeKey": "running", "parentTypeId": 17, "isHidden": false, "trimmable": true, "restricted": false}, "eventType": {"typeId": 9, "typeKey": "uncategorized", "sortOrder": 10}, "distance": 8868.6298828125, "duration": 2892.43994140625, "elapsedDuration": 2957.387939453125, "movingDuration": 2884.4500122070312, "elevationGain": 32.31999999284744, "elevationLoss": 32.07000000029802, "averageSpeed": 3.065999984741211, "maxSpeed": 5.011000156402588, "startLatitude": 43.0698945466429, "startLongitude": -89.40958544611931, "hasPolyline": true, "hasImages": false, "ownerId": 124379277, "ownerDisplayName": "5fddc451-c515-4112-b457-4b306d9f603d", "ownerFullName": "Vikranth Mandadi", "ownerProfileImageUrlSmall": "https://s3.amazonaws.com/garmin-connect-prod/profile_images/d97b2398-0e5d-4ff5-82f8-988261803023-prth.png", "ownerProfileImageUrlMedium": "https://s3.amazonaws.com/garmin-connect-prod/profile_images/d97b2398-0e5d-4ff5-82f8-988261803023-prfr.png", "ownerProfileImageUrlLarge": "https://s3.amazonaws.com/garmin-connect-prod/profile_images/d97b2398-0e5d-4ff5-82f8-988261803023-prof.png", "calories": 670.0, "bmrCalories": 72.0, "averageHR": 164.0, "maxHR": 193.0, "averageRunningCadenceInStepsPerMinute": 158.21875, "maxRunningCadenceInStepsPerMinute": 225.0, "steps": 7652, "userRoles": ["SCOPE_GOLF_API_READ", "SCOPE_ATP_READ", "SCOPE_DIVE_API_WRITE", "SCOPE_COMMUNITY_COURSE_ADMIN_READ", "SCOPE_DIVE_API_READ", "SCOPE_DI_OAUTH_2_CLIENT_READ", "SCOPE_CONNECT_WRITE", "SCOPE_COMMUNITY_COURSE_WRITE", "SCOPE_MESSAGE_GENERATION_READ", "SCOPE_DI_OAUTH_2_CLIENT_REVOCATION_ADMIN", "SCOPE_CONNECT_WEB_TEMPLATE_RENDER", "SCOPE_OMT_SUBSCRIPTION_ADMIN_READ", "SCOPE_CONNECT_NON_SOCIAL_SHARED_READ", "SCOPE_CONNECT_READ", "SCOPE_DI_OAUTH_2_TOKEN_ADMIN", "ROLE_CONNECTUSER", "ROLE_FITNESS_USER", "ROLE_WELLNESS_USER", "ROLE_OUTDOOR_USER"], "privacy": {"typeId": 2, "typeKey": "private"}, "userPro": false, "hasVideo": false, "timeZoneId": 152, "beginTimestamp": 1744844106000, "sportTypeId": 1, "avgPower": 323.0, "maxPower": 578.0, "aerobicTrainingEffect": 3.5999999046325684, "anaerobicTrainingEffect": 0.800000011920929, "normPower": 373.0, "avgVerticalOscillation": 8.55, "avgGroundContactTime": 245.10000610351562, "avgStrideLength": 113.10000000000001, "vO2MaxValue": 57.0, "avgVerticalRatio": 7.739999771118164, "deviceId": 3459366507, "minElevation": 261.20001220703125, "maxElevation": 277.0, "maxDoubleCadence": 225.0, "summarizedDiveInfo": {"summarizedDiveGases": []}, "maxVerticalSpeed": 0.600006103515625, "manufacturer": "GARMIN", "locationName": "Madison", "lapCount": 6, "endLatitude": 43.06957997381687, "endLongitude": -89.40973657183349, "waterEstimated": 747.0, "trainingEffectLabel": "VO2MAX", "activityTrainingLoad": 129.37460327148438, "minActivityLapDuration": 271.17401123046875, "aerobicTrainingEffectMessage": "IMPROVING_VO2_MAX_15", "anaerobicTrainingEffectMessage": "NO_ANAEROBIC_BENEFIT_0", "splitSummaries": [{"noOfSplits": 1, "totalAscent": 32.60000002384186, "duration": 2892.43994140625, "splitType": "INTERVAL_ACTIVE", "numClimbSends": 0, "maxElevationGain": 32.60000002384186, "averageElevationGain": 10.52999997138977, "maxDistance": 8868, "distance": 8868.6201171875, "averageSpeed": 3.065999984741211, "maxSpeed": 5.011000156402588, "numFalls": 0, "elevationLoss": 32.349999994039536}, {"noOfSplits": 3, "totalAscent": 0.0, "duration": 8.484999656677246, "splitType": "RWD_STAND", "numClimbSends": 0, "maxElevationGain": 0.0, "averageElevationGain": 0.0, "maxDistance": 9, "distance": 14.229999542236328, "averageSpeed": 1.6770000457763672, "maxSpeed": 2.127000093460083, "numFalls": 0, "elevationLoss": 0.0}, {"noOfSplits": 13, "totalAscent": 31.560000002384186, "duration": 2322.7119140625, "splitType": "RWD_RUN", "numClimbSends": 0, "maxElevationGain": 13.46000000834465, "averageElevationGain": 2.4099999964237213, "maxDistance": 2701, "distance": 7990.1298828125, "averageSpeed": 3.440000057220459, "maxSpeed": 5.011000156402588, "numFalls": 0, "elevationLoss": 28.62999999523163}, {"noOfSplits": 11, "totalAscent": 1.050000000745058, "duration": 561.0, "splitType": "RWD_WALK", "numClimbSends": 0, "maxElevationGain": 1.050000000745058, "averageElevationGain": 0.10000000149011612, "maxDistance": 227, "distance": 864.27001953125, "averageSpeed": 1.5410000085830688, "maxSpeed": 2.2300000190734863, "numFalls": 0, "elevationLoss": 3.7200000286102295}], "hasSplits": true, "moderateIntensityMinutes": 4, "vigorousIntensityMinutes": 44, "avgGradeAdjustedSpeed": 3.0460000038146973, "differenceBodyBattery": -9, "hasHeatMap": false, "fastestSplit_1000": 233.1269989013672, "fastestSplit_1609": 448.5570068359375, "fastestSplit_5000": 1534.8070068359375, "hrTimeInZone_1": 49.001, "hrTimeInZone_2": 394.921, "hrTimeInZone_3": 1352.191, "hrTimeInZone_4": 914.981, "hrTimeInZone_5": 171.001, "powerTimeInZone_1": 541.46, "powerTimeInZone_2": 367.135, "powerTimeInZone_3": 205.088, "powerTimeInZone_4": 687.55, "powerTimeInZone_5": 352.982, "manualActivity": false, "pr": false, "autoCalcCalories": false, "elevationCorrected": false, "atpActivity": false, "favorite": false, "decoDive": false, "parent": false, "purposeful": false}