{"activityId": 17023285673, "activityUUID": {"uuid": "7ba73ad4-fe4b-4ecf-904f-42d302bbd6b3"}, "activityName": "Madison Running", "userProfileId": 124379277, "isMultiSportParent": false, "activityTypeDTO": {"typeId": 1, "typeKey": "running", "parentTypeId": 17, "isHidden": false, "restricted": false, "trimmable": true}, "eventTypeDTO": {"typeId": 9, "typeKey": "uncategorized", "sortOrder": 10}, "accessControlRuleDTO": {"typeId": 2, "typeKey": "private"}, "timeZoneUnitDTO": {"unitId": 152, "unitKey": "America/Chicago", "factor": 0.0, "timeZone": "America/Chicago"}, "metadataDTO": {"isOriginal": true, "deviceApplicationInstallationId": 983493, "agentApplicationInstallationId": null, "agentString": null, "fileFormat": {"formatId": 7, "formatKey": "fit"}, "associatedCourseId": null, "lastUpdateDate": "2024-09-13T12:33:18.0", "uploadedDate": "2024-09-13T12:33:18.0", "videoUrl": null, "hasPolyline": true, "hasChartData": true, "hasHrTimeInZones": true, "hasPowerTimeInZones": true, "userInfoDto": {"userProfilePk": 124379277, "displayname": "5fddc451-c515-4112-b457-4b306d9f603d", "fullname": "Vikranth Mandadi", "profileImageUrlLarge": "https://s3.amazonaws.com/garmin-connect-prod/profile_images/d97b2398-0e5d-4ff5-82f8-988261803023-prof.png", "profileImageUrlMedium": "https://s3.amazonaws.com/garmin-connect-prod/profile_images/d97b2398-0e5d-4ff5-82f8-988261803023-prfr.png", "profileImageUrlSmall": "https://s3.amazonaws.com/garmin-connect-prod/profile_images/d97b2398-0e5d-4ff5-82f8-988261803023-prth.png", "userPro": false}, "childIds": [], "childActivityTypes": [], "sensors": null, "activityImages": [], "manufacturer": "GARMIN", "diveNumber": null, "lapCount": 3, "associatedWorkoutId": null, "isAtpActivity": null, "deviceMetaDataDTO": {"deviceId": "3459366507", "deviceTypePk": 36889, "deviceVersionPk": 983493}, "hasIntensityIntervals": false, "hasSplits": true, "eBikeMaxAssistModes": null, "eBikeBatteryUsage": null, "eBikeBatteryRemaining": null, "eBikeAssistModeInfoDTOList": null, "hasRunPowerWindData": true, "calendarEventInfo": null, "groupRideUUID": null, "hasHeatMap": false, "personalRecord": false, "autoCalcCalories": false, "favorite": false, "gcj02": false, "runPowerWindDataEnabled": true, "trimmed": false, "manualActivity": false, "elevationCorrected": false}, "summaryDTO": {"startTimeLocal": "2024-09-13T07:08:29.0", "startTimeGMT": "2024-09-13T12:08:29.0", "startLatitude": 43.06988373398781, "startLongitude": -89.40945158712566, "distance": 4356.55, "duration": 1431.977, "movingDuration": 1420.0, "elapsedDuration": 1470.382, "elevationGain": 26.84, "elevationLoss": 19.32, "maxElevation": 279.2, "minElevation": 263.8, "averageSpeed": 3.0420000553131104, "averageMovingSpeed": 3.0679928202024653, "maxSpeed": 4.739999771118164, "calories": 338.0, "bmrCalories": 35.0, "averageHR": 162.0, "maxHR": 182.0, "minHR": 87.0, "averageRunCadence": 175.890625, "maxRunCadence": 205.0, "averagePower": 326.0, "maxPower": 513.0, "minPower": 0.0, "normalizedPower": 330.0, "totalWork": 111.69397759437904, "groundContactTime": 248.3000030517578, "strideLength": 102.02999877929688, "verticalOscillation": 8.219999694824219, "trainingEffect": 3.0999999046325684, "anaerobicTrainingEffect": 0.0, "aerobicTrainingEffectMessage": "IMPACTING_TEMPO_22", "anaerobicTrainingEffectMessage": "NO_ANAEROBIC_BENEFIT_0", "verticalRatio": 8.069999694824219, "endLatitude": 43.0698636174202, "endLongitude": -89.40924815833569, "maxVerticalSpeed": 0.40002441406250006, "waterEstimated": 397.0, "trainingEffectLabel": "TEMPO", "activityTrainingLoad": 73.12417602539062, "minActivityLapDuration": 356.768, "moderateIntensityMinutes": 1, "vigorousIntensityMinutes": 22, "steps": 4228, "beginPotentialStamina": 100.0, "endPotentialStamina": 77.0, "minAvailableStamina": 77.0, "avgGradeAdjustedSpeed": 3.046999931335449, "differenceBodyBattery": -8}, "locationName": "Madison", "splitSummaries": [{"distance": 13.89, "duration": 12.744, "movingDuration": 0.0, "elevationGain": 0.0, "elevationLoss": 0.0, "averageSpeed": 1.090000033378601, "maxSpeed": 2.0339999198913574, "calories": 1.0, "bmrCalories": 0.0, "averageHR": 132.0, "maxHR": 176.0, "averageRunCadence": 43.25, "maxRunCadence": 173.0, "averagePower": 0.0, "maxPower": 0.0, "normalizedPower": 249.0, "strideLength": 0.0, "totalExerciseReps": 0, "avgVerticalSpeed": 0.0, "avgGradeAdjustedSpeed": 0.22599999606609344, "splitType": "RWD_STAND", "noOfSplits": 4, "maxElevationGain": 0.0, "averageElevationGain": 0.0, "maxDistance": 7, "maxDistanceWithPrecision": 7.55}, {"distance": 16.1, "duration": 6.75, "movingDuration": 3.0, "elevationGain": 0.0, "elevationLoss": 0.0, "averageSpeed": 2.384999990463257, "averageMovingSpeed": 3.1802468594209645, "maxSpeed": 2.071000099182129, "calories": 1.0, "bmrCalories": 0.0, "averageHR": 154.0, "maxHR": 157.0, "averageRunCadence": 16.59375, "maxRunCadence": 83.0, "averagePower": 12.0, "maxPower": 70.0, "normalizedPower": 193.0, "strideLength": 599.9581400234097, "verticalOscillation": 5.470000076293946, "totalExerciseReps": 0, "avgVerticalSpeed": 0.0, "avgGradeAdjustedSpeed": 0.9670000076293945, "splitType": "RWD_WALK", "noOfSplits": 2, "maxElevationGain": 0.0, "averageElevationGain": 0.0, "maxDistance": 11, "maxDistanceWithPrecision": 11.2}, {"distance": 4356.55, "duration": 1431.977, "movingDuration": 1419.0, "elevationGain": 26.24, "elevationLoss": 19.4, "averageSpeed": 3.0420000553131104, "averageMovingSpeed": 3.0701549011187454, "maxSpeed": 4.739999771118164, "calories": 338.0, "bmrCalories": 35.0, "averageHR": 162.0, "maxHR": 182.0, "averageRunCadence": 175.890625, "maxRunCadence": 205.0, "averagePower": 326.0, "maxPower": 513.0, "normalizedPower": 330.0, "groundContactTime": 248.3000030517578, "strideLength": 102.02999877929688, "verticalOscillation": 8.219999694824219, "verticalRatio": 8.069999694824219, "totalExerciseReps": 0, "avgVerticalSpeed": 0.004999999888241291, "avgGradeAdjustedSpeed": 3.0260000228881836, "splitType": "INTERVAL_ACTIVE", "noOfSplits": 1, "maxElevationGain": 26.24, "averageElevationGain": 26.24, "maxDistance": 4356, "maxDistanceWithPrecision": 4356.55}, {"distance": 4326.56, "duration": 1416.281, "movingDuration": 1409.652, "elevationGain": 26.24, "elevationLoss": 19.4, "averageSpeed": 3.055000066757202, "averageMovingSpeed": 3.060444764540885, "maxSpeed": 4.739999771118164, "calories": 335.0, "bmrCalories": 35.0, "averageHR": 162.0, "maxHR": 182.0, "averageRunCadence": 177.9375, "maxRunCadence": 205.0, "averagePower": 329.0, "maxPower": 513.0, "normalizedPower": 331.0, "groundContactTime": 248.3000030517578, "strideLength": 102.02999877929688, "verticalOscillation": 8.230000305175782, "verticalRatio": 8.069999694824219, "totalExerciseReps": 0, "avgVerticalSpeed": 0.004999999888241291, "avgGradeAdjustedSpeed": 3.059000015258789, "splitType": "RWD_RUN", "noOfSplits": 5, "maxElevationGain": 18.45, "averageElevationGain": 5.25, "maxDistance": 2538, "maxDistanceWithPrecision": 2538.65}]}