{"activityId": 16988970824, "activityUUID": {"uuid": "88b1b493-18c7-4f84-9831-dc96594f26e3"}, "activityName": "Madison Running", "userProfileId": 124379277, "isMultiSportParent": false, "activityTypeDTO": {"typeId": 1, "typeKey": "running", "parentTypeId": 17, "isHidden": false, "restricted": false, "trimmable": true}, "eventTypeDTO": {"typeId": 9, "typeKey": "uncategorized", "sortOrder": 10}, "accessControlRuleDTO": {"typeId": 2, "typeKey": "private"}, "timeZoneUnitDTO": {"unitId": 152, "unitKey": "America/Chicago", "factor": 0.0, "timeZone": "America/Chicago"}, "metadataDTO": {"isOriginal": true, "deviceApplicationInstallationId": 980891, "agentApplicationInstallationId": null, "agentString": null, "fileFormat": {"formatId": 7, "formatKey": "fit"}, "associatedCourseId": null, "lastUpdateDate": "2024-09-09T12:56:23.0", "uploadedDate": "2024-09-09T12:56:23.0", "videoUrl": null, "hasPolyline": true, "hasChartData": true, "hasHrTimeInZones": true, "hasPowerTimeInZones": true, "userInfoDto": {"userProfilePk": 124379277, "displayname": "5fddc451-c515-4112-b457-4b306d9f603d", "fullname": "Vikranth Mandadi", "profileImageUrlLarge": "https://s3.amazonaws.com/garmin-connect-prod/profile_images/d97b2398-0e5d-4ff5-82f8-988261803023-prof.png", "profileImageUrlMedium": "https://s3.amazonaws.com/garmin-connect-prod/profile_images/d97b2398-0e5d-4ff5-82f8-988261803023-prfr.png", "profileImageUrlSmall": "https://s3.amazonaws.com/garmin-connect-prod/profile_images/d97b2398-0e5d-4ff5-82f8-988261803023-prth.png", "userPro": false}, "childIds": [], "childActivityTypes": [], "sensors": null, "activityImages": [], "manufacturer": "GARMIN", "diveNumber": null, "lapCount": 4, "associatedWorkoutId": null, "isAtpActivity": null, "deviceMetaDataDTO": {"deviceId": "3459366507", "deviceTypePk": 36889, "deviceVersionPk": 980891}, "hasIntensityIntervals": false, "hasSplits": true, "eBikeMaxAssistModes": null, "eBikeBatteryUsage": null, "eBikeBatteryRemaining": null, "eBikeAssistModeInfoDTOList": null, "hasRunPowerWindData": true, "calendarEventInfo": null, "groupRideUUID": null, "hasHeatMap": false, "personalRecord": false, "trimmed": false, "gcj02": false, "runPowerWindDataEnabled": true, "autoCalcCalories": false, "favorite": false, "manualActivity": false, "elevationCorrected": false}, "summaryDTO": {"startTimeLocal": "2024-09-09T07:23:56.0", "startTimeGMT": "2024-09-09T12:23:56.0", "startLatitude": 43.06925802491605, "startLongitude": -89.40909275785089, "distance": 5923.56, "duration": 1805.201, "movingDuration": 1798.644, "elapsedDuration": 1809.923, "elevationGain": 7.83, "elevationLoss": 6.15, "maxElevation": 265.4, "minElevation": 258.8, "averageSpeed": 3.2809998989105225, "averageMovingSpeed": 3.2933476650119267, "maxSpeed": 3.7980000972747807, "calories": 469.0, "bmrCalories": 45.0, "averageHR": 179.0, "maxHR": 194.0, "minHR": 97.0, "averageRunCadence": 177.84375, "maxRunCadence": 190.0, "averagePower": 352.0, "maxPower": 447.0, "minPower": 0.0, "normalizedPower": 356.0, "totalWork": 152.0279139479048, "groundContactTime": 242.10000610351562, "strideLength": 110.04000244140626, "verticalOscillation": 8.509999847412109, "trainingEffect": 3.700000047683716, "anaerobicTrainingEffect": 0.0, "aerobicTrainingEffectMessage": "IMPROVING_VO2_MAX_15", "anaerobicTrainingEffectMessage": "NO_ANAEROBIC_BENEFIT_0", "verticalRatio": 7.739999771118164, "endLatitude": 43.0697182752192, "endLongitude": -89.40920214168727, "maxVerticalSpeed": 0.399993896484375, "waterEstimated": 501.0, "trainingEffectLabel": "VO2MAX", "activityTrainingLoad": 127.05085754394531, "minActivityLapDuration": 315.993, "moderateIntensityMinutes": 1, "vigorousIntensityMinutes": 29, "steps": 5364, "recoveryHeartRate": 13, "beginPotentialStamina": 100.0, "endPotentialStamina": 70.0, "minAvailableStamina": 70.0, "avgGradeAdjustedSpeed": 3.2920000553131104, "differenceBodyBattery": -9}, "locationName": "Madison", "splitSummaries": [{"distance": 5923.55, "duration": 1805.201, "movingDuration": 1798.0, "elevationGain": 7.15, "elevationLoss": 6.03, "averageSpeed": 3.2809998989105225, "averageMovingSpeed": 3.2945215821398777, "maxSpeed": 3.7980000972747807, "calories": 469.0, "bmrCalories": 45.0, "averageHR": 179.0, "maxHR": 194.0, "averageRunCadence": 177.828125, "maxRunCadence": 190.0, "averagePower": 352.0, "maxPower": 447.0, "normalizedPower": 356.0, "groundContactTime": 242.10000610351562, "strideLength": 110.04000244140626, "verticalOscillation": 8.509999847412109, "verticalRatio": 7.739999771118164, "totalExerciseReps": 0, "avgVerticalSpeed": 0.0010000000474974513, "avgGradeAdjustedSpeed": 3.2279999256134033, "splitType": "INTERVAL_ACTIVE", "noOfSplits": 1, "maxElevationGain": 7.15, "averageElevationGain": 7.15, "maxDistance": 5923, "maxDistanceWithPrecision": 5923.55}, {"distance": 0.0, "duration": 8.001, "movingDuration": 0.0, "elevationGain": 0.0, "elevationLoss": 0.0, "averageSpeed": 0.0, "maxSpeed": 0.0, "calories": 0.0, "bmrCalories": 0.0, "averageHR": 103.0, "maxHR": 105.0, "averageRunCadence": 0.0, "maxRunCadence": 0.0, "averagePower": 0.0, "maxPower": 0.0, "totalExerciseReps": 0, "avgVerticalSpeed": 0.0, "splitType": "RWD_STAND", "noOfSplits": 1, "maxElevationGain": 0.0, "averageElevationGain": 0.0, "maxDistance": 0, "maxDistanceWithPrecision": 0.0}, {"distance": 5923.55, "duration": 1800.948, "movingDuration": 1796.948, "elevationGain": 7.15, "elevationLoss": 6.03, "averageSpeed": 3.2890000343322754, "averageMovingSpeed": 3.289128731707734, "maxSpeed": 3.7980000972747807, "calories": 469.0, "bmrCalories": 45.0, "averageHR": 179.0, "maxHR": 194.0, "averageRunCadence": 178.625, "maxRunCadence": 190.0, "averagePower": 353.0, "maxPower": 447.0, "normalizedPower": 356.0, "groundContactTime": 242.10000610351562, "strideLength": 110.04000244140626, "verticalOscillation": 8.509999847412109, "verticalRatio": 7.739999771118164, "totalExerciseReps": 0, "avgVerticalSpeed": 0.0010000000474974513, "avgGradeAdjustedSpeed": 3.242000102996826, "splitType": "RWD_RUN", "noOfSplits": 2, "maxElevationGain": 7.15, "averageElevationGain": 3.36, "maxDistance": 5923, "maxDistanceWithPrecision": 5923.55}]}