{"activityId": 18714738937, "activityUUID": {"uuid": "a66c0b92-ad19-4b54-839e-16b3ad08aeed"}, "activityName": "Madison - Base", "userProfileId": 124379277, "isMultiSportParent": false, "activityTypeDTO": {"typeId": 1, "typeKey": "running", "parentTypeId": 17, "isHidden": false, "restricted": false, "trimmable": true}, "eventTypeDTO": {"typeId": 9, "typeKey": "uncategorized", "sortOrder": 10}, "accessControlRuleDTO": {"typeId": 2, "typeKey": "private"}, "timeZoneUnitDTO": {"unitId": 152, "unitKey": "America/Chicago", "factor": 0.0, "timeZone": "America/Chicago"}, "metadataDTO": {"isOriginal": true, "deviceApplicationInstallationId": 991247, "agentApplicationInstallationId": null, "agentString": null, "fileFormat": {"formatId": 7, "formatKey": "fit"}, "associatedCourseId": null, "lastUpdateDate": "2025-04-03T00:58:40.0", "uploadedDate": "2025-04-03T00:58:40.0", "videoUrl": null, "hasPolyline": true, "hasChartData": true, "hasHrTimeInZones": true, "hasPowerTimeInZones": true, "userInfoDto": {"userProfilePk": 124379277, "displayname": "5fddc451-c515-4112-b457-4b306d9f603d", "fullname": "Vikranth Mandadi", "profileImageUrlLarge": "https://s3.amazonaws.com/garmin-connect-prod/profile_images/d97b2398-0e5d-4ff5-82f8-988261803023-prof.png", "profileImageUrlMedium": "https://s3.amazonaws.com/garmin-connect-prod/profile_images/d97b2398-0e5d-4ff5-82f8-988261803023-prfr.png", "profileImageUrlSmall": "https://s3.amazonaws.com/garmin-connect-prod/profile_images/d97b2398-0e5d-4ff5-82f8-988261803023-prth.png", "userPro": false}, "childIds": [], "childActivityTypes": [], "sensors": null, "activityImages": [], "manufacturer": "GARMIN", "diveNumber": null, "lapCount": 6, "associatedWorkoutId": 3459366507, "isAtpActivity": null, "deviceMetaDataDTO": {"deviceId": "3459366507", "deviceTypePk": 36889, "deviceVersionPk": 991247}, "hasIntensityIntervals": false, "hasSplits": true, "eBikeMaxAssistModes": null, "eBikeBatteryUsage": null, "eBikeBatteryRemaining": null, "eBikeAssistModeInfoDTOList": null, "hasRunPowerWindData": false, "calendarEventInfo": null, "groupRideUUID": null, "hasHeatMap": false, "trimmed": false, "autoCalcCalories": false, "favorite": false, "personalRecord": false, "manualActivity": false, "runPowerWindDataEnabled": true, "gcj02": false, "elevationCorrected": false}, "summaryDTO": {"startTimeLocal": "2025-04-02T19:10:54.0", "startTimeGMT": "2025-04-03T00:10:54.0", "startLatitude": 43.068844713270664, "startLongitude": -89.40867089666426, "distance": 8059.1, "duration": 2647.856, "movingDuration": 2646.734, "elapsedDuration": 2647.856, "elevationGain": 23.95, "elevationLoss": 25.39, "maxElevation": 265.6, "minElevation": 256.6, "averageSpeed": 3.0439999103546143, "averageMovingSpeed": 3.0449225615019246, "maxSpeed": 3.368000030517578, "calories": 616.0, "bmrCalories": 65.0, "averageHR": 159.0, "maxHR": 180.0, "minHR": 94.0, "averageRunCadence": 168.3125, "maxRunCadence": 179.0, "averagePower": 328.0, "maxPower": 404.0, "minPower": 0.0, "normalizedPower": 330.0, "totalWork": 207.63624039980718, "groundContactTime": 262.0, "strideLength": 108.71999511718751, "verticalOscillation": 9.169999694824218, "trainingEffect": 3.299999952316284, "anaerobicTrainingEffect": 0.0, "aerobicTrainingEffectMessage": "IMPROVING_AEROBIC_BASE_8", "anaerobicTrainingEffectMessage": "NO_ANAEROBIC_BENEFIT_0", "verticalRatio": 8.430000305175781, "endLatitude": 43.069496070966125, "endLongitude": -89.40983564592898, "maxVerticalSpeed": 0.79998779296875, "waterEstimated": 735.0, "trainingEffectLabel": "AEROBIC_BASE", "activityTrainingLoad": 98.39418029785156, "minActivityLapDuration": 5.621, "directWorkoutFeel": 50, "directWorkoutRpe": 30, "directWorkoutComplianceScore": 69, "moderateIntensityMinutes": 2, "vigorousIntensityMinutes": 42, "steps": 7416, "beginPotentialStamina": 100.0, "endPotentialStamina": 80.0, "minAvailableStamina": 80.0, "avgGradeAdjustedSpeed": 3.055000066757202, "differenceBodyBattery": -7}, "locationName": "Madison", "splitSummaries": [{"distance": 8059.1, "duration": 2647.856, "movingDuration": 2647.0, "elevationGain": 23.91, "elevationLoss": 25.35, "averageSpeed": 3.0439999103546143, "averageMovingSpeed": 3.0446165839275596, "maxSpeed": 3.368000030517578, "calories": 616.0, "bmrCalories": 65.0, "averageHR": 159.0, "maxHR": 180.0, "averageRunCadence": 168.296875, "maxRunCadence": 179.0, "averagePower": 328.0, "maxPower": 404.0, "normalizedPower": 330.0, "groundContactTime": 262.0, "strideLength": 108.71999511718751, "verticalOscillation": 9.169999694824218, "verticalRatio": 8.430000305175781, "totalExerciseReps": 0, "avgVerticalSpeed": 0.0, "avgGradeAdjustedSpeed": 2.9760000705718994, "splitType": "INTERVAL_ACTIVE", "noOfSplits": 1, "maxElevationGain": 23.91, "averageElevationGain": 23.91, "maxDistance": 8059, "maxDistanceWithPrecision": 8059.1}, {"distance": 8059.1, "duration": 2647.602, "movingDuration": 2647.0, "elevationGain": 23.91, "elevationLoss": 25.35, "averageSpeed": 3.0439999103546143, "averageMovingSpeed": 3.0446165839275596, "maxSpeed": 3.368000030517578, "calories": 616.0, "bmrCalories": 65.0, "averageHR": 159.0, "maxHR": 180.0, "averageRunCadence": 168.296875, "maxRunCadence": 179.0, "averagePower": 328.0, "maxPower": 404.0, "normalizedPower": 330.0, "groundContactTime": 262.0, "strideLength": 108.71999511718751, "verticalOscillation": 9.169999694824218, "verticalRatio": 8.430000305175781, "totalExerciseReps": 0, "avgVerticalSpeed": 0.0, "avgGradeAdjustedSpeed": 2.9760000705718994, "splitType": "RWD_RUN", "noOfSplits": 1, "maxElevationGain": 23.91, "averageElevationGain": 23.91, "maxDistance": 8059, "maxDistanceWithPrecision": 8059.1}]}